{
  "Framework": "jasmine",
  "TestHarnessLocationMode": "SettingsFileAdjacent",
  "Compile": { "Mode": "External" },
  "References": [
    {
      "Path": "src/helpers.js"
    },
    {
      "Path": "src/Core.js"
    },
    {
      "Path": "src/Sandbox.js"
    },
    {
      "Path": "plugins/routing/UrlHash.js"
    },
    {
      "Path": "plugins/routing/Route.js"
    },
    {
      "Path": "plugins/routing/RouteConfig.js"
    },
    {
      "Path": "plugins/routing/routing.js"
    },
    {
      "Path": "plugins/mvp/Model.js"
    },
    {
      "Path": "plugins/mvp/HashSet.js"
    },
    {
      "Path": "plugins/mvp/Collection.js"
    },
    {
      "Path": "plugins/mvp/lib/UIEvent.js"
    },
    {
      "Path": "plugins/mvp/View.js"
    },
    {
      "Path": "plugins/mvp/Presenter.js"
    },
    {
      "Path": "plugins/mvp/mvp.js"
    },
    {
      "Path": "plugins/services/services.js"
    }
  ],
  "Tests": [
    {
      "Path": "tests",
      "Includes": [ "*.js" ]
    }
  ]
}